gradle.properties
hexdoc_hexflow/__gradle_version__.py
hexdoc_hexflow/__init__.py
hexdoc_hexflow/__version__.py
hexdoc_hexflow/_hooks.py
hexdoc_hexflow/py.typed
hexdoc_hexflow/_export/.gitignore
hexdoc_hexflow/_export/__init__.py
hexdoc_hexflow/_export/generated/__init__.py
hexdoc_hexflow/_export/generated/hexflow.hexdoc.json
hexdoc_hexflow/_export/generated/hexflow.patterns.hexdoc.json
hexdoc_hexflow/_export/generated/assets/hexcasting/patchouli_books/thehexbook/en_us/entries/hexflow.json
hexdoc_hexflow/_export/generated/assets/hexflow/lang/en_us.flatten.json5
hexdoc_hexflow/_export/generated/assets/hexflow/lang/en_us.json
hexdoc_hexflow/_export/generated/assets/hexflow/lang/zh_cn.json
hexdoc_hexflow/_templates/__init__.py
hexdoc_hexflow-0.4.1.0.1.dist-info/METADATA
hexdoc_hexflow-0.4.1.0.1.dist-info/WHEEL
hexdoc_hexflow-0.4.1.0.1.dist-info/entry_points.txt
hexdoc_hexflow-0.4.1.0.1.dist-info/licenses/LICENSE.txt
hexdoc_hexflow-0.4.1.0.1.dist-info/RECORD
