Metadata-Version: 2.4
Name: hexdoc-hexflow
Version: 0.4.1.0.1
Summary: Python web book docgen and hexdoc plugin for HexFlow.
Project-URL: Homepage, https://yukkuric.github.io/HexFlow/
Project-URL: Source, https://github.com/YukkuriC/HexFlow
Author: YukkuriC
License-File: LICENSE.txt
Keywords: hexdoc
Requires-Python: >=3.11
Requires-Dist: hexdoc-hexcasting~=0.11.2.1.0
Provides-Extra: dev
Requires-Dist: ruff~=0.11.2; extra == 'dev'
